{"title":"19. Larger Lymph Vessels","trackViews":true,"showMenuResultIcon":false,"viewGroupId":"","historyGroupId":"","videoZoom":"","scrolling":false,"transition":"appear","transDuration":0,"transDir":1,"wipeTrans":false,"slideLock":false,"navIndex":-1,"globalAudioId":"","thumbnailid":"","presenterRef":{"id":"none"},"showAnimationId":"","lmsId":"Slide19","width":720,"height":540,"resume":false,"background":{"type":"fill","fill":{"type":"linear","rotation":90,"colors":[{"kind":"color","rgb":"0xFFFFFF","alpha":100,"stop":0}]}},"id":"5uhkA0mcUKo","actionGroups":{"ActGrpOnSubmitButtonClick":{"kind":"actiongroup","actions":[]},"ActGrpOnNextButtonClick":{"kind":"actiongroup","actions":[{"kind":"gotoplay","window":"_current","wndtype":"normal","objRef":{"type":"string","value":"_player.69dXB9aaUer.6Zunaa40c6G"}}]},"ActGrpOnPrevButtonClick":{"kind":"actiongroup","actions":[{"kind":"gotoplay","window":"_current","wndtype":"normal","objRef":{"type":"string","value":"_player.69dXB9aaUer.6aES9RFtqWh"}}]},"NavigationRestrictionNextSlide_5uhkA0mcUKo":{"kind":"actiongroup","actions":[{"kind":"exe_actiongroup","id":"ActGrpOnNextButtonClick"}]},"NavigationRestrictionPreviousSlide_5uhkA0mcUKo":{"kind":"actiongroup","actions":[{"kind":"exe_actiongroup","id":"ActGrpOnPrevButtonClick"}]}},"events":[{"kind":"onbeforeslidein","actions":[{"kind":"if_action","condition":{"statement":{"kind":"compare","operator":"eq","valuea":"$WindowId","typea":"property","valueb":"_frame","typeb":"string"}},"thenActions":[{"kind":"set_frame_layout","name":"npnxnanbnsnfns01001000011"}],"elseActions":[{"kind":"set_window_control_layout","name":"npnxnanbnsnfns01001000011"}]}]},{"kind":"onsubmitslide","actions":[{"kind":"exe_actiongroup","id":"ActGrpOnSubmitButtonClick"}]},{"kind":"onkeypress","keycode":37,"shift":false,"ctrl":false,"alt":false,"actions":[{"kind":"gotoplay","window":"_current","wndtype":"normal","objRef":{"type":"string","value":"_player.69dXB9aaUer.6aES9RFtqWh"}}]},{"kind":"onkeypress","keycode":39,"shift":false,"ctrl":false,"alt":false,"actions":[{"kind":"gotoplay","window":"_current","wndtype":"normal","objRef":{"type":"string","value":"_player.69dXB9aaUer.6Zunaa40c6G"}}]},{"kind":"onnextslide","actions":[{"kind":"exe_actiongroup","id":"NavigationRestrictionNextSlide_5uhkA0mcUKo"}]},{"kind":"onprevslide","actions":[{"kind":"exe_actiongroup","id":"NavigationRestrictionPreviousSlide_5uhkA0mcUKo"}]},{"kind":"ontransitionin","actions":[{"kind":"adjustvar","variable":"_player.LastSlideViewed_6mkVidI9kET","operator":"set","value":{"type":"string","value":"_player."}},{"kind":"adjustvar","variable":"_player.LastSlideViewed_6mkVidI9kET","operator":"add","value":{"type":"property","value":"$AbsoluteId"}}]}],"slideLayers":[{"enableSeek":true,"enableReplay":true,"timeline":{"duration":5000,"events":[{"kind":"ontimelinetick","time":0,"actions":[{"kind":"show","transition":"appear","objRef":{"type":"string","value":"620j0rjHOVu"}},{"kind":"show","transition":"appear","objRef":{"type":"string","value":"5wF8YkybWSl"}},{"kind":"show","transition":"appear","objRef":{"type":"string","value":"5VcRgv7xHQ7"}},{"kind":"show","transition":"appear","objRef":{"type":"string","value":"5flbT1vc1Zd"}},{"kind":"show","transition":"appear","objRef":{"type":"string","value":"6gkTI7QsONj"}},{"kind":"show","transition":"appear","objRef":{"type":"string","value":"5h62KbjOmlr"}},{"kind":"show","transition":"appear","objRef":{"type":"string","value":"6KYooFlj8re"}},{"kind":"show","transition":"appear","objRef":{"type":"string","value":"6GzvR82IAoC"}},{"kind":"show","transition":"appear","objRef":{"type":"string","value":"6UjADzFwbH5.6UjADzFwbH5_expandinglabel.content_scroll_6UjADzFwbH5"}},{"kind":"show","transition":"appear","objRef":{"type":"string","value":"6UjADzFwbH5.6UjADzFwbH5_expandinglabel.content_scroll_6UjADzFwbH5.5h3L0WERMps"}},{"kind":"show","transition":"appear","objRef":{"type":"string","value":"6UjADzFwbH5"}},{"kind":"show","transition":"appear","objRef":{"type":"string","value":"6iL3QKOJQOS.6iL3QKOJQOS_expandinglabel.content_scroll_6iL3QKOJQOS"}},{"kind":"show","transition":"appear","objRef":{"type":"string","value":"6iL3QKOJQOS.6iL3QKOJQOS_expandinglabel.content_scroll_6iL3QKOJQOS.6DhJa3JhUfS"}},{"kind":"show","transition":"appear","objRef":{"type":"string","value":"6iL3QKOJQOS"}},{"kind":"show","transition":"appear","objRef":{"type":"string","value":"6V2rwT8otdK"}}]}]},"objects":[{"kind":"vectorshape","rotation":0,"accType":"image","cliptobounds":false,"defaultAction":"","imagelib":[{"kind":"imagedata","assetId":44,"id":"01","url":"story_content/5sdNNFRhE3E_DX908_DY908.swf","type":"normal","altText":"G1031.png","width":650,"height":908,"mobiledx":0,"mobiledy":0}],"shapemaskId":"","xPos":0,"yPos":48,"tabIndex":4,"tabEnabled":true,"xOffset":0,"yOffset":0,"rotateXPos":162.5,"rotateYPos":227,"scaleX":100,"scaleY":100,"alpha":100,"depth":1,"scrolling":true,"shuffleLock":false,"data":{"hotlinkId":"","accState":0,"vectorData":{"left":-5,"top":-5,"right":328,"bottom":457,"altText":"G1031.png","pngfb":false,"pr":{"l":"Lib","i":363}},"html5data":{"xPos":-2,"yPos":-2,"width":327,"height":456,"strokewidth":3}},"width":325,"height":454,"resume":false,"useHandCursor":true,"id":"620j0rjHOVu"},{"kind":"vectorshape","rotation":0,"accType":"text","cliptobounds":false,"defaultAction":"","shapemaskId":"","xPos":-1,"yPos":-2,"tabIndex":0,"tabEnabled":true,"xOffset":0,"yOffset":0,"rotateXPos":360.5,"rotateYPos":24,"scaleX":100,"scaleY":100,"alpha":100,"depth":2,"scrolling":true,"shuffleLock":false,"data":{"hotlinkId":"","accState":0,"vectorData":{"left":0,"top":0,"right":721,"bottom":48,"altText":"Rectangle 1","pngfb":false,"pr":{"l":"Lib","i":65}},"html5data":{"xPos":-1,"yPos":-1,"width":722,"height":49,"strokewidth":0}},"width":721,"height":48,"resume":false,"useHandCursor":true,"id":"5wF8YkybWSl"},{"kind":"vectorshape","rotation":0,"accType":"text","cliptobounds":false,"defaultAction":"","shapemaskId":"","xPos":0,"yPos":502,"tabIndex":15,"tabEnabled":true,"xOffset":0,"yOffset":0,"rotateXPos":360.5,"rotateYPos":20,"scaleX":100,"scaleY":100,"alpha":100,"depth":3,"scrolling":true,"shuffleLock":false,"data":{"hotlinkId":"","accState":0,"vectorData":{"left":0,"top":0,"right":721,"bottom":40,"altText":"Rectangle 2","pngfb":false,"pr":{"l":"Lib","i":49}},"html5data":{"xPos":-1,"yPos":-1,"width":722,"height":41,"strokewidth":0}},"width":721,"height":40,"resume":false,"useHandCursor":true,"id":"5VcRgv7xHQ7"},{"kind":"vectorshape","rotation":0,"accType":"button","cliptobounds":false,"defaultAction":"onrelease","textLib":[{"kind":"textdata","uniqueId":"5flbT1vc1Zd_-40649406","id":"01","linkId":"txt__default_5flbT1vc1Zd","type":"vectortext","xPos":0,"yPos":0,"width":0,"height":0,"shadowIndex":-1,"vectortext":{"left":0,"top":0,"right":68,"bottom":22,"pngfb":false,"pr":{"l":"Lib","i":192}}}],"shapemaskId":"","xPos":624,"yPos":510,"tabIndex":17,"tabEnabled":true,"xOffset":0,"yOffset":0,"rotateXPos":44,"rotateYPos":12,"scaleX":100,"scaleY":100,"alpha":100,"depth":4,"scrolling":true,"shuffleLock":false,"data":{"hotlinkId":"","accState":0,"vectorData":{"left":-2,"top":-2,"right":89,"bottom":25,"altText":"  Next","pngfb":false,"pr":{"l":"Lib","i":52}},"html5data":{"xPos":-1,"yPos":-1,"width":89,"height":25,"strokewidth":2}},"width":88,"height":24,"resume":false,"useHandCursor":true,"id":"5flbT1vc1Zd","events":[{"kind":"onrelease","actions":[{"kind":"gotoplay","window":"_current","wndtype":"normal","objRef":{"type":"string","value":"_player.69dXB9aaUer.6Zunaa40c6G"}}]}]},{"kind":"vectorshape","rotation":0,"accType":"button","cliptobounds":false,"defaultAction":"onrelease","textLib":[{"kind":"textdata","uniqueId":"6gkTI7QsONj_2124268285","id":"01","linkId":"txt__default_6gkTI7QsONj","type":"vectortext","xPos":0,"yPos":0,"width":0,"height":0,"shadowIndex":-1,"vectortext":{"left":0,"top":0,"right":90,"bottom":22,"pngfb":false,"pr":{"l":"Lib","i":51}}}],"shapemaskId":"","xPos":8,"yPos":510,"tabIndex":16,"tabEnabled":true,"xOffset":0,"yOffset":0,"rotateXPos":52,"rotateYPos":12,"scaleX":100,"scaleY":100,"alpha":100,"depth":5,"scrolling":true,"shuffleLock":false,"data":{"hotlinkId":"","accState":0,"vectorData":{"left":-2,"top":-2,"right":105,"bottom":25,"altText":"Previous","pngfb":false,"pr":{"l":"Lib","i":50}},"html5data":{"xPos":-1,"yPos":-1,"width":105,"height":25,"strokewidth":2}},"width":104,"height":24,"resume":false,"useHandCursor":true,"id":"6gkTI7QsONj","events":[{"kind":"onrelease","actions":[{"kind":"gotoplay","window":"_current","wndtype":"normal","objRef":{"type":"string","value":"_player.69dXB9aaUer.6aES9RFtqWh"}}]}]},{"kind":"vectorshape","rotation":0,"accType":"text","cliptobounds":false,"defaultAction":"","textLib":[{"kind":"textdata","uniqueId":"5h62KbjOmlr_-1596709906","id":"01","linkId":"txt__default_5h62KbjOmlr","type":"vectortext","xPos":0,"yPos":0,"width":0,"height":0,"shadowIndex":-1,"vectortext":{"left":0,"top":0,"right":212,"bottom":28,"pngfb":false,"pr":{"l":"Lib","i":364}}}],"shapemaskId":"","xPos":8,"yPos":6,"tabIndex":1,"tabEnabled":true,"xOffset":0,"yOffset":0,"rotateXPos":251,"rotateYPos":16.5,"scaleX":100,"scaleY":100,"alpha":100,"depth":6,"scrolling":true,"shuffleLock":false,"data":{"hotlinkId":"","accState":0,"vectorData":{"left":0,"top":0,"right":502,"bottom":33,"altText":"2A   Larger Lymph Vessels","pngfb":false,"pr":{"l":"Lib","i":201}},"html5data":{"xPos":-1,"yPos":-1,"width":503,"height":34,"strokewidth":0}},"width":502,"height":33,"resume":false,"useHandCursor":true,"id":"5h62KbjOmlr"},{"kind":"vectorshape","rotation":0,"accType":"text","cliptobounds":false,"defaultAction":"","textLib":[{"kind":"textdata","uniqueId":"6KYooFlj8re_-1964840445","id":"01","linkId":"txt__default_6KYooFlj8re","type":"vectortext","xPos":0,"yPos":0,"width":0,"height":0,"shadowIndex":-1,"vectortext":{"left":0,"top":0,"right":68,"bottom":28,"pngfb":false,"pr":{"l":"Lib","i":365}}}],"shapemaskId":"","xPos":636,"yPos":6,"tabIndex":2,"tabEnabled":true,"xOffset":0,"yOffset":0,"rotateXPos":39,"rotateYPos":16.5,"scaleX":100,"scaleY":100,"alpha":100,"depth":7,"scrolling":true,"shuffleLock":false,"data":{"hotlinkId":"","accState":0,"vectorData":{"left":0,"top":0,"right":78,"bottom":33,"altText":"19","pngfb":false,"pr":{"l":"Lib","i":199}},"html5data":{"xPos":-1,"yPos":-1,"width":79,"height":34,"strokewidth":0}},"width":78,"height":33,"resume":false,"useHandCursor":true,"id":"6KYooFlj8re"},{"kind":"vectorshape","rotation":0,"accType":"text","cliptobounds":false,"defaultAction":"","textLib":[{"kind":"textdata","uniqueId":"6GzvR82IAoC_337188278","id":"01","linkId":"txt__default_6GzvR82IAoC","type":"vectortext","xPos":0,"yPos":0,"width":0,"height":0,"shadowIndex":-1,"vectortext":{"left":0,"top":0,"right":381,"bottom":409,"pngfb":false,"pr":{"l":"Lib","i":367}}}],"shapemaskId":"","xPos":338,"yPos":44,"tabIndex":3,"tabEnabled":true,"xOffset":0,"yOffset":0,"rotateXPos":195,"rotateYPos":207,"scaleX":100,"scaleY":100,"alpha":100,"depth":8,"scrolling":true,"shuffleLock":false,"data":{"hotlinkId":"","accState":0,"vectorData":{"left":0,"top":0,"right":390,"bottom":414,"altText":"Lymphatic capillaries coalesce repeatedly, forming progressively larger lymphatic vessels called lymphatic trunks that ultimately converge to form the largest lymphatic vessels in the body, the lymphatic ducts. Lymphatic ducts empty into the great veins in the neck. \nThe thoracic duct is the largest lymphatic vessel in the body. As illustrated by the darker shaded area in accompanying diagram, it collects lymph bilaterally from tissues below the diaphragm     , and conducts it superiorly. In the posterior thorax, the thoracic duct collects lymph bilaterally from the thoracic wall. \nIn the neck, near its terminus, the thoracic duct accepts lymph from the left side of the head and neck via the left jugular trunk, from the left upper limb via the left subclavian trunk, and from the left thoracic viscera via the left bronchomediastinal trunk. \nFrom the thoracic duct, lymph from these three quadrants of the body drains into venous blood at the left venous angle, which is the convergence of the left internal jugular vein     with the left subclavian vein    . ","pngfb":false,"pr":{"l":"Lib","i":366}},"html5data":{"xPos":-1,"yPos":-1,"width":391,"height":415,"strokewidth":0}},"width":390,"height":414,"resume":false,"useHandCursor":true,"id":"6GzvR82IAoC"},{"kind":"stategroup","objects":[{"kind":"expandinglabel","animationtype":"full","showclosebutton":false,"contentheight":0,"borderwidth":1,"arrowxpos":467,"arrowypos":-18,"objects":[{"kind":"scrollarea","contentwidth":457,"contentheight":29,"objects":[{"kind":"vectorshape","rotation":0,"accType":"text","cliptobounds":false,"defaultAction":"","textLib":[{"kind":"textdata","uniqueId":"5h3L0WERMps_126414651","id":"01","linkId":"txt__default_5h3L0WERMps","type":"vectortext","xPos":0,"yPos":0,"width":0,"height":0,"shadowIndex":-1,"vectortext":{"left":0,"top":0,"right":339,"bottom":18,"pngfb":false,"pr":{"l":"Lib","i":370}}}],"shapemaskId":"","xPos":0,"yPos":0,"tabIndex":14,"tabEnabled":true,"xOffset":0,"yOffset":0,"rotateXPos":228.5,"rotateYPos":9,"scaleX":100,"scaleY":100,"alpha":100,"depth":1100,"scrolling":true,"shuffleLock":false,"data":{"hotlinkId":"","accState":0,"vectorData":{"left":0,"top":0,"right":457,"bottom":18,"altText":"drains venous blood from the left upper limb and axilla","pngfb":false,"pr":{"l":"Lib","i":369}},"html5data":{"xPos":-1,"yPos":-1,"width":458,"height":19,"strokewidth":0}},"width":457,"height":18,"resume":false,"useHandCursor":true,"id":"5h3L0WERMps"}],"shapemaskId":"","xPos":0,"yPos":0,"tabIndex":13,"tabEnabled":true,"xOffset":0,"yOffset":0,"rotateXPos":228.5,"rotateYPos":14.5,"scaleX":100,"scaleY":100,"alpha":100,"rotation":0,"depth":0,"scrolling":true,"shuffleLock":false,"width":457,"height":29,"resume":false,"useHandCursor":true,"id":"content_scroll_6UjADzFwbH5"}],"textLib":[{"kind":"textdata","uniqueId":"6gwCGzUM5eL_826447961","id":"01","linkId":"txt__default_6gwCGzUM5eL","type":"vectortext","xPos":0,"yPos":0,"width":0,"height":0,"shadowIndex":-1,"vectortext":{"left":0,"top":0,"right":153,"bottom":19,"pngfb":false,"pr":{"l":"Lib","i":371}}}],"shapemaskId":"","xPos":-453,"yPos":32,"tabIndex":12,"tabEnabled":true,"xOffset":0,"yOffset":0,"rotateXPos":0,"rotateYPos":0,"scaleX":100,"scaleY":100,"alpha":100,"rotation":0,"depth":1,"scrolling":true,"shuffleLock":false,"colors":[{"kind":"color","name":"border","fill":{"type":"linear","rotation":0,"colors":[{"kind":"color","rgb":"0xFAC090","alpha":100,"stop":0}]}},{"kind":"color","name":"bg","fill":{"type":"linear","rotation":0,"colors":[{"kind":"color","rgb":"0xF2F2F2","alpha":100,"stop":0}]}}],"data":{"hotlinkId":"","accState":0,"vectorData":{"left":0,"top":0,"right":457,"bottom":19,"altText":"the left subclavian vein","pngfb":false,"pr":{"l":"Lib","i":368}},"html5data":{"xPos":-1,"yPos":-1,"width":458,"height":20,"strokewidth":0}},"width":467,"height":68,"resume":false,"useHandCursor":true,"id":"6UjADzFwbH5_expandinglabel","events":[{"kind":"onclickoutside","actions":[{"kind":"if_action","condition":{"statement":{"kind":"compare","operator":"eq","valuea":"$Expanded","typea":"property","valueb":true,"typeb":"boolean"}},"thenActions":[{"kind":"object_action","command":"hidecomplete","objRef":{"type":"string","value":"_this"}}]}]}]},{"kind":"vectorshape","rotation":0,"accType":"button","cliptobounds":false,"defaultAction":"onrelease","shapemaskId":"","xPos":0,"yPos":0,"tabIndex":11,"tabEnabled":true,"xOffset":0,"yOffset":0,"rotateXPos":14,"rotateYPos":14,"scaleX":100,"scaleY":100,"alpha":100,"depth":2,"scrolling":true,"shuffleLock":false,"data":{"hotlinkId":"","accState":0,"vectorData":{"left":0,"top":0,"right":28,"bottom":28,"altText":"Marker","pngfb":false,"pr":{"l":"Lib","i":43}},"html5data":{"xPos":-1,"yPos":-1,"width":29,"height":29,"strokewidth":0}},"markerType":"none","width":28,"height":28,"resume":false,"useHandCursor":true,"id":"6UjADzFwbH5"}],"actionstates":[{"kind":"state","name":"_default","actions":[{"kind":"setobjstate","stateRef":{"type":"string","value":"_default"},"objRef":{"type":"string","value":"6UjADzFwbH5"}}],"clickdef":[{"kind":"objref","type":"string","value":"6UjADzFwbH5"}]}],"shapemaskId":"","xPos":688,"yPos":430,"tabIndex":20,"tabEnabled":false,"xOffset":0,"yOffset":0,"rotateXPos":14,"rotateYPos":14,"scaleX":100,"scaleY":100,"alpha":100,"rotation":0,"depth":9,"scrolling":true,"shuffleLock":false,"width":28,"height":28,"resume":false,"useHandCursor":true,"id":"6UjADzFwbH5","actionGroups":{"_show":{"kind":"actiongroup","actions":[{"kind":"show","transition":"appear","objRef":{"type":"string","value":"6UjADzFwbH5_expandinglabel"}},{"kind":"show","transition":"appear","objRef":{"type":"string","value":"6UjADzFwbH5"}}]}},"events":[{"kind":"onrollover","actions":[{"kind":"bringtofront","value":{"type":"string","value":"_this"}},{"kind":"object_action","command":"showtitle","objRef":{"type":"string","value":"6UjADzFwbH5_expandinglabel"}}]},{"kind":"onrollout","actions":[{"kind":"object_action","command":"hidetitle","objRef":{"type":"string","value":"6UjADzFwbH5_expandinglabel"}}]},{"kind":"onrelease","actions":[{"kind":"bringtofront","value":{"type":"string","value":"_this"}},{"kind":"object_action","command":"togglecontent","objRef":{"type":"string","value":"6UjADzFwbH5_expandinglabel"}}]},{"kind":"ontransitionin","actions":[{"kind":"exe_actiongroup","id":"_show"}]}]},{"kind":"stategroup","objects":[{"kind":"expandinglabel","animationtype":"full","showclosebutton":false,"contentheight":0,"borderwidth":1,"arrowxpos":386,"arrowypos":-18,"objects":[{"kind":"scrollarea","contentwidth":376,"contentheight":30,"objects":[{"kind":"vectorshape","rotation":0,"accType":"text","cliptobounds":false,"defaultAction":"","textLib":[{"kind":"textdata","uniqueId":"6DhJa3JhUfS_-101965957","id":"01","linkId":"txt__default_6DhJa3JhUfS","type":"vectortext","xPos":0,"yPos":0,"width":0,"height":0,"shadowIndex":-1,"vectortext":{"left":0,"top":0,"right":367,"bottom":18,"pngfb":false,"pr":{"l":"Lib","i":374}}}],"shapemaskId":"","xPos":0,"yPos":0,"tabIndex":10,"tabEnabled":true,"xOffset":0,"yOffset":0,"rotateXPos":188,"rotateYPos":9,"scaleX":100,"scaleY":100,"alpha":100,"depth":1100,"scrolling":true,"shuffleLock":false,"data":{"hotlinkId":"","accState":0,"vectorData":{"left":0,"top":0,"right":376,"bottom":18,"altText":"drains venous blood from the left side of the head and neck","pngfb":false,"pr":{"l":"Lib","i":373}},"html5data":{"xPos":-1,"yPos":-1,"width":377,"height":19,"strokewidth":0}},"width":376,"height":18,"resume":false,"useHandCursor":true,"id":"6DhJa3JhUfS"}],"shapemaskId":"","xPos":0,"yPos":0,"tabIndex":9,"tabEnabled":true,"xOffset":0,"yOffset":0,"rotateXPos":188,"rotateYPos":15,"scaleX":100,"scaleY":100,"alpha":100,"rotation":0,"depth":0,"scrolling":true,"shuffleLock":false,"width":376,"height":30,"resume":false,"useHandCursor":true,"id":"content_scroll_6iL3QKOJQOS"}],"textLib":[{"kind":"textdata","uniqueId":"6m3TlkGoHhJ_1689554304","id":"01","linkId":"txt__default_6m3TlkGoHhJ","type":"vectortext","xPos":0,"yPos":0,"width":0,"height":0,"shadowIndex":-1,"vectortext":{"left":0,"top":0,"right":186,"bottom":19,"pngfb":false,"pr":{"l":"Lib","i":375}}}],"shapemaskId":"","xPos":-372,"yPos":32,"tabIndex":8,"tabEnabled":true,"xOffset":0,"yOffset":0,"rotateXPos":0,"rotateYPos":0,"scaleX":100,"scaleY":100,"alpha":100,"rotation":0,"depth":1,"scrolling":true,"shuffleLock":false,"colors":[{"kind":"color","name":"border","fill":{"type":"linear","rotation":0,"colors":[{"kind":"color","rgb":"0xFAC090","alpha":100,"stop":0}]}},{"kind":"color","name":"bg","fill":{"type":"linear","rotation":0,"colors":[{"kind":"color","rgb":"0xF2F2F2","alpha":100,"stop":0}]}}],"data":{"hotlinkId":"","accState":0,"vectorData":{"left":0,"top":0,"right":376,"bottom":19,"altText":"the left internal jugular vein","pngfb":false,"pr":{"l":"Lib","i":372}},"html5data":{"xPos":-1,"yPos":-1,"width":377,"height":20,"strokewidth":0}},"width":386,"height":69,"resume":false,"useHandCursor":true,"id":"6iL3QKOJQOS_expandinglabel","events":[{"kind":"onclickoutside","actions":[{"kind":"if_action","condition":{"statement":{"kind":"compare","operator":"eq","valuea":"$Expanded","typea":"property","valueb":true,"typeb":"boolean"}},"thenActions":[{"kind":"object_action","command":"hidecomplete","objRef":{"type":"string","value":"_this"}}]}]}]},{"kind":"vectorshape","rotation":0,"accType":"button","cliptobounds":false,"defaultAction":"onrelease","shapemaskId":"","xPos":0,"yPos":0,"tabIndex":7,"tabEnabled":true,"xOffset":0,"yOffset":0,"rotateXPos":14,"rotateYPos":14,"scaleX":100,"scaleY":100,"alpha":100,"depth":2,"scrolling":true,"shuffleLock":false,"data":{"hotlinkId":"","accState":0,"vectorData":{"left":0,"top":0,"right":28,"bottom":28,"altText":"Marker","pngfb":false,"pr":{"l":"Lib","i":43}},"html5data":{"xPos":-1,"yPos":-1,"width":29,"height":29,"strokewidth":0}},"markerType":"none","width":28,"height":28,"resume":false,"useHandCursor":true,"id":"6iL3QKOJQOS"}],"actionstates":[{"kind":"state","name":"_default","actions":[{"kind":"setobjstate","stateRef":{"type":"string","value":"_default"},"objRef":{"type":"string","value":"6iL3QKOJQOS"}}],"clickdef":[{"kind":"objref","type":"string","value":"6iL3QKOJQOS"}]}],"shapemaskId":"","xPos":482,"yPos":430,"tabIndex":19,"tabEnabled":false,"xOffset":0,"yOffset":0,"rotateXPos":14,"rotateYPos":14,"scaleX":100,"scaleY":100,"alpha":100,"rotation":0,"depth":10,"scrolling":true,"shuffleLock":false,"width":28,"height":28,"resume":false,"useHandCursor":true,"id":"6iL3QKOJQOS","actionGroups":{"_show":{"kind":"actiongroup","actions":[{"kind":"show","transition":"appear","objRef":{"type":"string","value":"6iL3QKOJQOS_expandinglabel"}},{"kind":"show","transition":"appear","objRef":{"type":"string","value":"6iL3QKOJQOS"}}]}},"events":[{"kind":"onrollover","actions":[{"kind":"bringtofront","value":{"type":"string","value":"_this"}},{"kind":"object_action","command":"showtitle","objRef":{"type":"string","value":"6iL3QKOJQOS_expandinglabel"}}]},{"kind":"onrollout","actions":[{"kind":"object_action","command":"hidetitle","objRef":{"type":"string","value":"6iL3QKOJQOS_expandinglabel"}}]},{"kind":"onrelease","actions":[{"kind":"bringtofront","value":{"type":"string","value":"_this"}},{"kind":"object_action","command":"togglecontent","objRef":{"type":"string","value":"6iL3QKOJQOS_expandinglabel"}}]},{"kind":"ontransitionin","actions":[{"kind":"exe_actiongroup","id":"_show"}]}]},{"kind":"stategroup","objects":[{"kind":"expandinglabel","animationtype":"full","showclosebutton":false,"contentheight":0,"borderwidth":1,"arrowxpos":112,"arrowypos":-18,"textLib":[{"kind":"textdata","uniqueId":"6PWTqLo4JxI_1707978997","id":"01","linkId":"txt__default_6PWTqLo4JxI","type":"vectortext","xPos":0,"yPos":0,"width":0,"height":0,"shadowIndex":-1,"vectortext":{"left":0,"top":0,"right":214,"bottom":38,"pngfb":false,"pr":{"l":"Lib","i":377}}}],"shapemaskId":"","xPos":-98,"yPos":32,"tabIndex":6,"tabEnabled":true,"xOffset":0,"yOffset":0,"rotateXPos":0,"rotateYPos":0,"scaleX":100,"scaleY":100,"alpha":100,"rotation":0,"depth":1,"scrolling":true,"shuffleLock":false,"colors":[{"kind":"color","name":"border","fill":{"type":"linear","rotation":0,"colors":[{"kind":"color","rgb":"0xFAC090","alpha":100,"stop":0}]}},{"kind":"color","name":"bg","fill":{"type":"linear","rotation":0,"colors":[{"kind":"color","rgb":"0xF2F2F2","alpha":100,"stop":0}]}}],"data":{"hotlinkId":"","accState":0,"vectorData":{"left":0,"top":0,"right":214,"bottom":38,"altText":"i.e. the lower limbs, the pelvis and perineum, and the abdomen ","pngfb":false,"pr":{"l":"Lib","i":376}},"html5data":{"xPos":-1,"yPos":-1,"width":215,"height":39,"strokewidth":0}},"width":224,"height":69,"resume":false,"useHandCursor":true,"id":"6V2rwT8otdK_expandinglabel","events":[{"kind":"onclickoutside","actions":[{"kind":"if_action","condition":{"statement":{"kind":"compare","operator":"eq","valuea":"$Expanded","typea":"property","valueb":true,"typeb":"boolean"}},"thenActions":[{"kind":"object_action","command":"hidecomplete","objRef":{"type":"string","value":"_this"}}]}]}]},{"kind":"vectorshape","rotation":0,"accType":"button","cliptobounds":false,"defaultAction":"onrelease","shapemaskId":"","xPos":0,"yPos":0,"tabIndex":5,"tabEnabled":true,"xOffset":0,"yOffset":0,"rotateXPos":14,"rotateYPos":14,"scaleX":100,"scaleY":100,"alpha":100,"depth":2,"scrolling":true,"shuffleLock":false,"data":{"hotlinkId":"","accState":0,"vectorData":{"left":0,"top":0,"right":28,"bottom":28,"altText":"Marker","pngfb":false,"pr":{"l":"Lib","i":43}},"html5data":{"xPos":-1,"yPos":-1,"width":29,"height":29,"strokewidth":0}},"markerType":"none","width":28,"height":28,"resume":false,"useHandCursor":true,"id":"6V2rwT8otdK"}],"actionstates":[{"kind":"state","name":"_default","actions":[{"kind":"setobjstate","stateRef":{"type":"string","value":"_default"},"objRef":{"type":"string","value":"6V2rwT8otdK"}}],"clickdef":[{"kind":"objref","type":"string","value":"6V2rwT8otdK"}]}],"shapemaskId":"","xPos":574,"yPos":206,"tabIndex":18,"tabEnabled":false,"xOffset":0,"yOffset":0,"rotateXPos":14,"rotateYPos":14,"scaleX":100,"scaleY":100,"alpha":100,"rotation":0,"depth":11,"scrolling":true,"shuffleLock":false,"width":28,"height":28,"resume":false,"useHandCursor":true,"id":"6V2rwT8otdK","actionGroups":{"_show":{"kind":"actiongroup","actions":[{"kind":"show","transition":"appear","objRef":{"type":"string","value":"6V2rwT8otdK_expandinglabel"}},{"kind":"show","transition":"appear","objRef":{"type":"string","value":"6V2rwT8otdK"}}]}},"events":[{"kind":"onrollover","actions":[{"kind":"bringtofront","value":{"type":"string","value":"_this"}},{"kind":"object_action","command":"showtitle","objRef":{"type":"string","value":"6V2rwT8otdK_expandinglabel"}}]},{"kind":"onrollout","actions":[{"kind":"object_action","command":"hidetitle","objRef":{"type":"string","value":"6V2rwT8otdK_expandinglabel"}}]},{"kind":"ontransitionin","actions":[{"kind":"exe_actiongroup","id":"_show"}]}]}],"startTime":-1,"elapsedTimeMode":"normal","useHandCursor":false,"resume":false,"kind":"slidelayer","isBaseLayer":true}]}
