{"title":"14. Summary: Blood Supply to the Foregut","trackViews":true,"showMenuResultIcon":false,"viewGroupId":"","historyGroupId":"","videoZoom":"","scrolling":false,"transition":"appear","transDuration":0,"transDir":1,"wipeTrans":false,"slideLock":false,"navIndex":-1,"globalAudioId":"","thumbnailid":"","slideNumberInScene":14,"includeInSlideCounts":true,"presenterRef":{"id":"none"},"showAnimationId":"","lmsId":"Slide14","width":720,"height":540,"resume":false,"background":{"type":"fill","fill":{"type":"linear","rotation":90,"colors":[{"kind":"color","rgb":"0xFFFFFF","alpha":100,"stop":0}]}},"id":"5Uley7zfCTN","actionGroups":{"ActGrpOnSubmitButtonClick":{"kind":"actiongroup","actions":[]},"ActGrpOnNextButtonClick":{"kind":"actiongroup","actions":[{"kind":"gotoplay","window":"_current","wndtype":"normal","objRef":{"type":"string","value":"_player.5nmsFnPWvrY.6ZHe9m8SXxW"}}]},"ActGrpOnPrevButtonClick":{"kind":"actiongroup","actions":[{"kind":"gotoplay","window":"_current","wndtype":"normal","objRef":{"type":"string","value":"_player.5nmsFnPWvrY.65kJKI22yJJ"}}]},"NavigationRestrictionNextSlide_5Uley7zfCTN":{"kind":"actiongroup","actions":[{"kind":"exe_actiongroup","id":"ActGrpOnNextButtonClick"}]},"NavigationRestrictionPreviousSlide_5Uley7zfCTN":{"kind":"actiongroup","actions":[{"kind":"exe_actiongroup","id":"ActGrpOnPrevButtonClick"}]}},"events":[{"kind":"onbeforeslidein","actions":[{"kind":"if_action","condition":{"statement":{"kind":"compare","operator":"eq","valuea":"$WindowId","typea":"property","valueb":"_frame","typeb":"string"}},"thenActions":[{"kind":"set_frame_layout","name":"npnxabnsnfns01001000011"}],"elseActions":[{"kind":"set_window_control_layout","name":"npnxabnsnfns01001000011"}]}]},{"kind":"onsubmitslide","actions":[{"kind":"exe_actiongroup","id":"ActGrpOnSubmitButtonClick"}]},{"kind":"onkeypress","keycode":39,"shift":false,"ctrl":false,"alt":false,"actions":[{"kind":"gotoplay","window":"_current","wndtype":"normal","objRef":{"type":"string","value":"_player.5nmsFnPWvrY.6ZHe9m8SXxW"}}]},{"kind":"onkeypress","keycode":37,"shift":false,"ctrl":false,"alt":false,"actions":[{"kind":"gotoplay","window":"_current","wndtype":"normal","objRef":{"type":"string","value":"_player.5nmsFnPWvrY.65kJKI22yJJ"}}]},{"kind":"onnextslide","actions":[{"kind":"exe_actiongroup","id":"NavigationRestrictionNextSlide_5Uley7zfCTN"}]},{"kind":"onprevslide","actions":[{"kind":"exe_actiongroup","id":"NavigationRestrictionPreviousSlide_5Uley7zfCTN"}]},{"kind":"ontransitionin","actions":[{"kind":"adjustvar","variable":"_player.LastSlideViewed_5tzbW9RgNda","operator":"set","value":{"type":"string","value":"_player."}},{"kind":"adjustvar","variable":"_player.LastSlideViewed_5tzbW9RgNda","operator":"add","value":{"type":"property","value":"$AbsoluteId"}}]}],"slideLayers":[{"enableSeek":true,"enableReplay":true,"timeline":{"duration":5000,"events":[{"kind":"ontimelinetick","time":0,"actions":[{"kind":"show","transition":"appear","objRef":{"type":"string","value":"6T5pw6KerdC"}},{"kind":"show","transition":"appear","objRef":{"type":"string","value":"6n92TVA5OoU"}},{"kind":"show","transition":"appear","objRef":{"type":"string","value":"6AYksNPukcL"}},{"kind":"show","transition":"appear","objRef":{"type":"string","value":"6434kx0CvKR"}},{"kind":"show","transition":"appear","objRef":{"type":"string","value":"6o7QlYZmldO"}},{"kind":"show","transition":"appear","objRef":{"type":"string","value":"6haZqo3NFEW"}},{"kind":"show","transition":"appear","objRef":{"type":"string","value":"67peWng7iwn"}},{"kind":"show","transition":"appear","objRef":{"type":"string","value":"5nBZnIbZFhO"}},{"kind":"show","transition":"appear","objRef":{"type":"string","value":"6Q3bJnxVXPC"}},{"kind":"show","transition":"appear","objRef":{"type":"string","value":"6anDUtgfvYO"}},{"kind":"show","transition":"appear","objRef":{"type":"string","value":"5s19mv5k8lP"}},{"kind":"show","transition":"appear","objRef":{"type":"string","value":"67RCwcEFD0f"}},{"kind":"show","transition":"appear","objRef":{"type":"string","value":"6ejDxaOLIoX"}},{"kind":"show","transition":"appear","objRef":{"type":"string","value":"6KSf5bjKtRi"}}]}]},"objects":[{"kind":"vectorshape","rotation":0,"accType":"text","cliptobounds":false,"defaultAction":"","shapemaskId":"","xPos":-1,"yPos":-2,"tabIndex":0,"tabEnabled":true,"xOffset":0,"yOffset":0,"rotateXPos":360.5,"rotateYPos":24,"scaleX":100,"scaleY":100,"alpha":100,"depth":1,"scrolling":true,"shuffleLock":false,"data":{"hotlinkId":"","accState":0,"vectorData":{"left":0,"top":0,"right":721,"bottom":48,"altText":"Rectangle 1","pngfb":false,"pr":{"l":"Lib","i":35}},"html5data":{"xPos":0,"yPos":0,"width":721,"height":48,"strokewidth":0}},"width":721,"height":48,"resume":false,"useHandCursor":true,"id":"6T5pw6KerdC"},{"kind":"vectorshape","rotation":0,"accType":"text","cliptobounds":false,"defaultAction":"","textLib":[{"kind":"textdata","uniqueId":"6n92TVA5OoU_1877343180","id":"01","linkId":"txt__default_6n92TVA5OoU","type":"vectortext","xPos":0,"yPos":0,"width":0,"height":0,"shadowIndex":-1,"vectortext":{"left":0,"top":0,"right":361,"bottom":29,"pngfb":false,"pr":{"l":"Lib","i":776}}}],"shapemaskId":"","xPos":-2,"yPos":6,"tabIndex":1,"tabEnabled":true,"xOffset":0,"yOffset":0,"rotateXPos":269,"rotateYPos":17,"scaleX":100,"scaleY":100,"alpha":100,"depth":2,"scrolling":true,"shuffleLock":false,"data":{"hotlinkId":"","accState":0,"vectorData":{"left":0,"top":0,"right":538,"bottom":34,"altText":"10.2   Summary: Blood Supply to the Foregut","pngfb":false,"pr":{"l":"Lib","i":775}},"html5data":{"xPos":0,"yPos":0,"width":538,"height":34,"strokewidth":0}},"width":538,"height":34,"resume":false,"useHandCursor":true,"id":"6n92TVA5OoU"},{"kind":"vectorshape","rotation":0,"accType":"text","cliptobounds":false,"defaultAction":"","shapemaskId":"","xPos":0,"yPos":502,"tabIndex":16,"tabEnabled":true,"xOffset":0,"yOffset":0,"rotateXPos":360.5,"rotateYPos":20,"scaleX":100,"scaleY":100,"alpha":100,"depth":3,"scrolling":true,"shuffleLock":false,"data":{"hotlinkId":"","accState":0,"vectorData":{"left":0,"top":0,"right":721,"bottom":40,"altText":"Rectangle 2","pngfb":false,"pr":{"l":"Lib","i":38}},"html5data":{"xPos":0,"yPos":0,"width":721,"height":40,"strokewidth":0}},"width":721,"height":40,"resume":false,"useHandCursor":true,"id":"6AYksNPukcL"},{"kind":"vectorshape","rotation":0,"accType":"button","cliptobounds":false,"defaultAction":"onrelease","textLib":[{"kind":"textdata","uniqueId":"6434kx0CvKR_-170057248","id":"01","linkId":"txt__default_6434kx0CvKR","type":"vectortext","xPos":0,"yPos":0,"width":0,"height":0,"shadowIndex":-1,"vectortext":{"left":0,"top":0,"right":64,"bottom":22,"pngfb":false,"pr":{"l":"Lib","i":42}}}],"shapemaskId":"","xPos":624,"yPos":510,"tabIndex":18,"tabEnabled":true,"xOffset":0,"yOffset":0,"rotateXPos":44,"rotateYPos":12,"scaleX":100,"scaleY":100,"alpha":100,"depth":4,"scrolling":true,"shuffleLock":false,"data":{"hotlinkId":"","accState":0,"vectorData":{"left":-2,"top":-2,"right":89,"bottom":25,"altText":"Next","pngfb":false,"pr":{"l":"Lib","i":41}},"html5data":{"xPos":0,"yPos":0,"width":88,"height":24,"strokewidth":2}},"width":88,"height":24,"resume":false,"useHandCursor":true,"id":"6434kx0CvKR","events":[{"kind":"onrelease","actions":[{"kind":"gotoplay","window":"_current","wndtype":"normal","objRef":{"type":"string","value":"_player.5nmsFnPWvrY.6ZHe9m8SXxW"}}]}]},{"kind":"vectorshape","rotation":0,"accType":"button","cliptobounds":false,"defaultAction":"onrelease","textLib":[{"kind":"textdata","uniqueId":"6o7QlYZmldO_-2102996392","id":"01","linkId":"txt__default_6o7QlYZmldO","type":"vectortext","xPos":0,"yPos":0,"width":0,"height":0,"shadowIndex":-1,"vectortext":{"left":0,"top":0,"right":90,"bottom":22,"pngfb":false,"pr":{"l":"Lib","i":40}}}],"shapemaskId":"","xPos":8,"yPos":510,"tabIndex":17,"tabEnabled":true,"xOffset":0,"yOffset":0,"rotateXPos":52,"rotateYPos":12,"scaleX":100,"scaleY":100,"alpha":100,"depth":5,"scrolling":true,"shuffleLock":false,"data":{"hotlinkId":"","accState":0,"vectorData":{"left":-2,"top":-2,"right":105,"bottom":25,"altText":"Previous","pngfb":false,"pr":{"l":"Lib","i":39}},"html5data":{"xPos":0,"yPos":0,"width":104,"height":24,"strokewidth":2}},"width":104,"height":24,"resume":false,"useHandCursor":true,"id":"6o7QlYZmldO","events":[{"kind":"onrelease","actions":[{"kind":"gotoplay","window":"_current","wndtype":"normal","objRef":{"type":"string","value":"_player.5nmsFnPWvrY.65kJKI22yJJ"}}]}]},{"kind":"vectorshape","rotation":0,"accType":"text","cliptobounds":false,"defaultAction":"","textLib":[{"kind":"textdata","uniqueId":"6haZqo3NFEW_-498916048","id":"01","linkId":"txt__default_6haZqo3NFEW","type":"vectortext","xPos":0,"yPos":0,"width":0,"height":0,"shadowIndex":-1,"vectortext":{"left":0,"top":0,"right":68,"bottom":28,"pngfb":false,"pr":{"l":"Lib","i":295}}}],"shapemaskId":"","xPos":636,"yPos":6,"tabIndex":2,"tabEnabled":true,"xOffset":0,"yOffset":0,"rotateXPos":39,"rotateYPos":16.5,"scaleX":100,"scaleY":100,"alpha":100,"depth":6,"scrolling":true,"shuffleLock":false,"data":{"hotlinkId":"","accState":0,"vectorData":{"left":0,"top":0,"right":78,"bottom":33,"altText":"14","pngfb":false,"pr":{"l":"Lib","i":156}},"html5data":{"xPos":0,"yPos":0,"width":78,"height":33,"strokewidth":0}},"width":78,"height":33,"resume":false,"useHandCursor":true,"id":"6haZqo3NFEW"},{"kind":"vectorshape","rotation":0,"accType":"image","cliptobounds":false,"defaultAction":"","imagelib":[{"kind":"imagedata","assetId":131,"id":"01","url":"story_content/6Ot8uLamvh4_DX896_DY896.swf","type":"normal","altText":"G4.106.png","width":783,"height":895,"mobiledx":0,"mobiledy":0}],"shapemaskId":"","xPos":325,"yPos":52,"tabIndex":4,"tabEnabled":true,"xOffset":0,"yOffset":0,"rotateXPos":196,"rotateYPos":224,"scaleX":100,"scaleY":100,"alpha":100,"depth":7,"scrolling":true,"shuffleLock":false,"data":{"hotlinkId":"","accState":0,"vectorData":{"left":0,"top":0,"right":392,"bottom":448,"altText":"G4.106.png","pngfb":false,"pr":{"l":"Lib","i":777}},"html5data":{"xPos":0,"yPos":0,"width":392,"height":448,"strokewidth":0}},"width":392,"height":448,"resume":false,"useHandCursor":true,"id":"67peWng7iwn"},{"kind":"vectorshape","rotation":0,"accType":"text","cliptobounds":false,"defaultAction":"","textLib":[{"kind":"textdata","uniqueId":"5nBZnIbZFhO_1596502540","id":"01","linkId":"txt__default_5nBZnIbZFhO","type":"vectortext","xPos":0,"yPos":0,"width":0,"height":0,"shadowIndex":-1,"vectortext":{"left":0,"top":0,"right":56,"bottom":24,"pngfb":false,"pr":{"l":"Lib","i":778}}}],"shapemaskId":"","xPos":645,"yPos":464,"tabIndex":13,"tabEnabled":true,"xOffset":0,"yOffset":0,"rotateXPos":33,"rotateYPos":14.5,"scaleX":100,"scaleY":100,"alpha":100,"depth":8,"scrolling":true,"shuffleLock":false,"data":{"hotlinkId":"","accState":0,"vectorData":{"left":0,"top":0,"right":66,"bottom":29,"altText":"G4.106","pngfb":false,"pr":{"l":"Lib","i":211}},"html5data":{"xPos":0,"yPos":0,"width":66,"height":29,"strokewidth":0}},"width":66,"height":29,"resume":false,"useHandCursor":true,"id":"5nBZnIbZFhO"},{"kind":"vectorshape","rotation":0,"accType":"text","cliptobounds":false,"defaultAction":"","textLib":[{"kind":"textdata","uniqueId":"6Q3bJnxVXPC_302424053","id":"01","linkId":"txt__default_6Q3bJnxVXPC","type":"vectortext","xPos":0,"yPos":0,"width":0,"height":0,"shadowIndex":-1,"vectortext":{"left":0,"top":0,"right":344,"bottom":441,"pngfb":false,"pr":{"l":"Lib","i":780}}}],"shapemaskId":"","xPos":0,"yPos":48,"tabIndex":3,"tabEnabled":true,"xOffset":0,"yOffset":0,"rotateXPos":176,"rotateYPos":223,"scaleX":100,"scaleY":100,"alpha":100,"depth":9,"scrolling":true,"shuffleLock":false,"data":{"hotlinkId":"","accState":0,"vectorData":{"left":0,"top":0,"right":352,"bottom":446,"altText":"This figure includes the branches of the celiac trunk that you’ve learned about so far. There are more that you will learn about as you dissect.\nDon’t panic! You will learn and remember this vascular tree because you will discover it for yourself when you dissect it!\nRecap: Try to answer the following questions before clicking on the buttons to check the answers. You need to know this information before you start your dissection of the foregut!\nWhich two arteries run along the lesser curvature of the stomach in the lesser omentum?\nWhich two arteries run along the greater curvature of the stomach in the greater omentum?\nWhich arteries access the stomach by passing through the gastrosplenic ligament?\nWhich artery accesses the liver by passing through the hepatoduodenal ligament?\nWhich artery runs through the splenorenal ligament?","pngfb":false,"pr":{"l":"Lib","i":779}},"html5data":{"xPos":0,"yPos":0,"width":352,"height":446,"strokewidth":0}},"width":352,"height":446,"resume":false,"useHandCursor":true,"id":"6Q3bJnxVXPC"},{"kind":"stategroup","objects":[{"kind":"expandinglabel","animationtype":"full","showclosebutton":false,"contentheight":0,"borderwidth":2,"arrowxpos":120,"arrowypos":-18,"textLib":[{"kind":"textdata","uniqueId":"6a9BLplKtuK_-1918247892","id":"01","linkId":"txt__default_6a9BLplKtuK","type":"vectortext","xPos":0,"yPos":0,"width":0,"height":0,"shadowIndex":-1,"vectortext":{"left":0,"top":0,"right":217,"bottom":19,"pngfb":false,"pr":{"l":"Lib","i":782}}}],"shapemaskId":"","xPos":-106,"yPos":32,"tabIndex":6,"tabEnabled":true,"xOffset":0,"yOffset":0,"rotateXPos":0,"rotateYPos":0,"scaleX":100,"scaleY":100,"alpha":100,"rotation":0,"depth":1,"scrolling":true,"shuffleLock":false,"colors":[{"kind":"color","name":"border","fill":{"type":"linear","rotation":0,"colors":[{"kind":"color","rgb":"0xFAC090","alpha":100,"stop":0}]}},{"kind":"color","name":"bg","fill":{"type":"linear","rotation":0,"colors":[{"kind":"color","rgb":"0xF2F2F2","alpha":100,"stop":0}]}}],"data":{"hotlinkId":"","accState":0,"vectorData":{"left":0,"top":0,"right":230,"bottom":19,"altText":"the left and right gastric arteries","pngfb":false,"pr":{"l":"Lib","i":781}},"html5data":{"xPos":0,"yPos":0,"width":230,"height":19,"strokewidth":0}},"width":240,"height":52,"resume":false,"useHandCursor":true,"id":"6anDUtgfvYO_expandinglabel","events":[{"kind":"onclickoutside","actions":[{"kind":"if_action","condition":{"statement":{"kind":"compare","operator":"eq","valuea":"$Expanded","typea":"property","valueb":true,"typeb":"boolean"}},"thenActions":[{"kind":"object_action","command":"hidecomplete","objRef":{"type":"string","value":"_this"}}]}]}]},{"kind":"vectorshape","rotation":0,"accType":"button","cliptobounds":false,"defaultAction":"onrelease","shapemaskId":"","xPos":0,"yPos":0,"tabIndex":5,"tabEnabled":true,"xOffset":0,"yOffset":0,"rotateXPos":14,"rotateYPos":14,"scaleX":100,"scaleY":100,"alpha":100,"depth":2,"scrolling":true,"shuffleLock":false,"data":{"hotlinkId":"","accState":0,"vectorData":{"left":0,"top":0,"right":28,"bottom":28,"altText":"Marker","pngfb":false,"pr":{"l":"Lib","i":32}},"html5data":{"xPos":0,"yPos":0,"width":28,"height":28,"strokewidth":0}},"markerType":"none","width":28,"height":28,"resume":false,"useHandCursor":true,"id":"6anDUtgfvYO"}],"actionstates":[{"kind":"state","name":"_default","actions":[{"kind":"setobjstate","stateRef":{"type":"string","value":"_default"},"objRef":{"type":"string","value":"6anDUtgfvYO"}}],"clickdef":[{"kind":"objref","type":"string","value":"6anDUtgfvYO"}]}],"shapemaskId":"","xPos":260,"yPos":282,"tabIndex":19,"tabEnabled":false,"xOffset":0,"yOffset":0,"rotateXPos":14,"rotateYPos":14,"scaleX":100,"scaleY":100,"alpha":100,"rotation":0,"depth":10,"scrolling":true,"shuffleLock":false,"width":28,"height":28,"resume":false,"useHandCursor":true,"id":"6anDUtgfvYO","actionGroups":{"_show":{"kind":"actiongroup","actions":[{"kind":"show","transition":"appear","objRef":{"type":"string","value":"6anDUtgfvYO_expandinglabel"}},{"kind":"show","transition":"appear","objRef":{"type":"string","value":"6anDUtgfvYO"}}]}},"events":[{"kind":"onrollover","actions":[{"kind":"bringtofront","value":{"type":"string","value":"_this"}},{"kind":"object_action","command":"showtitle","objRef":{"type":"string","value":"6anDUtgfvYO_expandinglabel"}}]},{"kind":"onrollout","actions":[{"kind":"object_action","command":"hidetitle","objRef":{"type":"string","value":"6anDUtgfvYO_expandinglabel"}}]},{"kind":"ontransitionin","actions":[{"kind":"exe_actiongroup","id":"_show"}]}]},{"kind":"stategroup","objects":[{"kind":"expandinglabel","animationtype":"full","showclosebutton":false,"contentheight":0,"borderwidth":2,"arrowxpos":152,"arrowypos":-18,"textLib":[{"kind":"textdata","uniqueId":"63nJbIF9rUj_899589040","id":"01","linkId":"txt__default_63nJbIF9rUj","type":"vectortext","xPos":0,"yPos":0,"width":0,"height":0,"shadowIndex":-1,"vectortext":{"left":0,"top":0,"right":274,"bottom":19,"pngfb":false,"pr":{"l":"Lib","i":784}}}],"shapemaskId":"","xPos":-138,"yPos":32,"tabIndex":8,"tabEnabled":true,"xOffset":0,"yOffset":0,"rotateXPos":0,"rotateYPos":0,"scaleX":100,"scaleY":100,"alpha":100,"rotation":0,"depth":1,"scrolling":true,"shuffleLock":false,"colors":[{"kind":"color","name":"border","fill":{"type":"linear","rotation":0,"colors":[{"kind":"color","rgb":"0xFAC090","alpha":100,"stop":0}]}},{"kind":"color","name":"bg","fill":{"type":"linear","rotation":0,"colors":[{"kind":"color","rgb":"0xF2F2F2","alpha":100,"stop":0}]}}],"data":{"hotlinkId":"","accState":0,"vectorData":{"left":0,"top":0,"right":294,"bottom":19,"altText":"the left and right gastro-omental arteries","pngfb":false,"pr":{"l":"Lib","i":783}},"html5data":{"xPos":0,"yPos":0,"width":294,"height":19,"strokewidth":0}},"width":304,"height":52,"resume":false,"useHandCursor":true,"id":"5s19mv5k8lP_expandinglabel","events":[{"kind":"onclickoutside","actions":[{"kind":"if_action","condition":{"statement":{"kind":"compare","operator":"eq","valuea":"$Expanded","typea":"property","valueb":true,"typeb":"boolean"}},"thenActions":[{"kind":"object_action","command":"hidecomplete","objRef":{"type":"string","value":"_this"}}]}]}]},{"kind":"vectorshape","rotation":0,"accType":"button","cliptobounds":false,"defaultAction":"onrelease","shapemaskId":"","xPos":0,"yPos":0,"tabIndex":7,"tabEnabled":true,"xOffset":0,"yOffset":0,"rotateXPos":14,"rotateYPos":14,"scaleX":100,"scaleY":100,"alpha":100,"depth":2,"scrolling":true,"shuffleLock":false,"data":{"hotlinkId":"","accState":0,"vectorData":{"left":0,"top":0,"right":28,"bottom":28,"altText":"Marker","pngfb":false,"pr":{"l":"Lib","i":32}},"html5data":{"xPos":0,"yPos":0,"width":28,"height":28,"strokewidth":0}},"markerType":"none","width":28,"height":28,"resume":false,"useHandCursor":true,"id":"5s19mv5k8lP"}],"actionstates":[{"kind":"state","name":"_default","actions":[{"kind":"setobjstate","stateRef":{"type":"string","value":"_default"},"objRef":{"type":"string","value":"5s19mv5k8lP"}}],"clickdef":[{"kind":"objref","type":"string","value":"5s19mv5k8lP"}]}],"shapemaskId":"","xPos":268,"yPos":326,"tabIndex":20,"tabEnabled":false,"xOffset":0,"yOffset":0,"rotateXPos":14,"rotateYPos":14,"scaleX":100,"scaleY":100,"alpha":100,"rotation":0,"depth":11,"scrolling":true,"shuffleLock":false,"width":28,"height":28,"resume":false,"useHandCursor":true,"id":"5s19mv5k8lP","actionGroups":{"_show":{"kind":"actiongroup","actions":[{"kind":"show","transition":"appear","objRef":{"type":"string","value":"5s19mv5k8lP_expandinglabel"}},{"kind":"show","transition":"appear","objRef":{"type":"string","value":"5s19mv5k8lP"}}]}},"events":[{"kind":"onrollover","actions":[{"kind":"bringtofront","value":{"type":"string","value":"_this"}},{"kind":"object_action","command":"showtitle","objRef":{"type":"string","value":"5s19mv5k8lP_expandinglabel"}}]},{"kind":"onrollout","actions":[{"kind":"object_action","command":"hidetitle","objRef":{"type":"string","value":"5s19mv5k8lP_expandinglabel"}}]},{"kind":"ontransitionin","actions":[{"kind":"exe_actiongroup","id":"_show"}]}]},{"kind":"stategroup","objects":[{"kind":"expandinglabel","animationtype":"full","showclosebutton":false,"contentheight":0,"borderwidth":2,"arrowxpos":218,"arrowypos":-18,"textLib":[{"kind":"textdata","uniqueId":"5ZsB4no6UPY_-1136156571","id":"01","linkId":"txt__default_5ZsB4no6UPY","type":"vectortext","xPos":0,"yPos":0,"width":0,"height":0,"shadowIndex":-1,"vectortext":{"left":0,"top":0,"right":407,"bottom":19,"pngfb":false,"pr":{"l":"Lib","i":786}}}],"shapemaskId":"","xPos":-204,"yPos":32,"tabIndex":10,"tabEnabled":true,"xOffset":0,"yOffset":0,"rotateXPos":0,"rotateYPos":0,"scaleX":100,"scaleY":100,"alpha":100,"rotation":0,"depth":1,"scrolling":true,"shuffleLock":false,"colors":[{"kind":"color","name":"border","fill":{"type":"linear","rotation":0,"colors":[{"kind":"color","rgb":"0xFAC090","alpha":100,"stop":0}]}},{"kind":"color","name":"bg","fill":{"type":"linear","rotation":0,"colors":[{"kind":"color","rgb":"0xF2F2F2","alpha":100,"stop":0}]}}],"data":{"hotlinkId":"","accState":0,"vectorData":{"left":0,"top":0,"right":426,"bottom":19,"altText":"the short gastric arteries and the left gastro-omental arteries","pngfb":false,"pr":{"l":"Lib","i":785}},"html5data":{"xPos":0,"yPos":0,"width":426,"height":19,"strokewidth":0}},"width":436,"height":52,"resume":false,"useHandCursor":true,"id":"67RCwcEFD0f_expandinglabel","events":[{"kind":"onclickoutside","actions":[{"kind":"if_action","condition":{"statement":{"kind":"compare","operator":"eq","valuea":"$Expanded","typea":"property","valueb":true,"typeb":"boolean"}},"thenActions":[{"kind":"object_action","command":"hidecomplete","objRef":{"type":"string","value":"_this"}}]}]}]},{"kind":"vectorshape","rotation":0,"accType":"button","cliptobounds":false,"defaultAction":"onrelease","shapemaskId":"","xPos":0,"yPos":0,"tabIndex":9,"tabEnabled":true,"xOffset":0,"yOffset":0,"rotateXPos":14,"rotateYPos":14,"scaleX":100,"scaleY":100,"alpha":100,"depth":2,"scrolling":true,"shuffleLock":false,"data":{"hotlinkId":"","accState":0,"vectorData":{"left":0,"top":0,"right":28,"bottom":28,"altText":"Marker","pngfb":false,"pr":{"l":"Lib","i":32}},"html5data":{"xPos":0,"yPos":0,"width":28,"height":28,"strokewidth":0}},"markerType":"none","width":28,"height":28,"resume":false,"useHandCursor":true,"id":"67RCwcEFD0f"}],"actionstates":[{"kind":"state","name":"_default","actions":[{"kind":"setobjstate","stateRef":{"type":"string","value":"_default"},"objRef":{"type":"string","value":"67RCwcEFD0f"}}],"clickdef":[{"kind":"objref","type":"string","value":"67RCwcEFD0f"}]}],"shapemaskId":"","xPos":240,"yPos":374,"tabIndex":21,"tabEnabled":false,"xOffset":0,"yOffset":0,"rotateXPos":14,"rotateYPos":14,"scaleX":100,"scaleY":100,"alpha":100,"rotation":0,"depth":12,"scrolling":true,"shuffleLock":false,"width":28,"height":28,"resume":false,"useHandCursor":true,"id":"67RCwcEFD0f","actionGroups":{"_show":{"kind":"actiongroup","actions":[{"kind":"show","transition":"appear","objRef":{"type":"string","value":"67RCwcEFD0f_expandinglabel"}},{"kind":"show","transition":"appear","objRef":{"type":"string","value":"67RCwcEFD0f"}}]}},"events":[{"kind":"onrollover","actions":[{"kind":"bringtofront","value":{"type":"string","value":"_this"}},{"kind":"object_action","command":"showtitle","objRef":{"type":"string","value":"67RCwcEFD0f_expandinglabel"}}]},{"kind":"onrollout","actions":[{"kind":"object_action","command":"hidetitle","objRef":{"type":"string","value":"67RCwcEFD0f_expandinglabel"}}]},{"kind":"ontransitionin","actions":[{"kind":"exe_actiongroup","id":"_show"}]}]},{"kind":"stategroup","objects":[{"kind":"expandinglabel","animationtype":"full","showclosebutton":false,"contentheight":0,"borderwidth":2,"arrowxpos":99,"arrowypos":-18,"textLib":[{"kind":"textdata","uniqueId":"5duI5i26yYR_2103062132","id":"01","linkId":"txt__default_5duI5i26yYR","type":"vectortext","xPos":0,"yPos":0,"width":0,"height":0,"shadowIndex":-1,"vectortext":{"left":0,"top":0,"right":168,"bottom":19,"pngfb":false,"pr":{"l":"Lib","i":788}}}],"shapemaskId":"","xPos":-85,"yPos":32,"tabIndex":12,"tabEnabled":true,"xOffset":0,"yOffset":0,"rotateXPos":0,"rotateYPos":0,"scaleX":100,"scaleY":100,"alpha":100,"rotation":0,"depth":1,"scrolling":true,"shuffleLock":false,"colors":[{"kind":"color","name":"border","fill":{"type":"linear","rotation":0,"colors":[{"kind":"color","rgb":"0xFAC090","alpha":100,"stop":0}]}},{"kind":"color","name":"bg","fill":{"type":"linear","rotation":0,"colors":[{"kind":"color","rgb":"0xF2F2F2","alpha":100,"stop":0}]}}],"data":{"hotlinkId":"","accState":0,"vectorData":{"left":0,"top":0,"right":188,"bottom":19,"altText":"the hepatic artery proper","pngfb":false,"pr":{"l":"Lib","i":787}},"html5data":{"xPos":0,"yPos":0,"width":188,"height":19,"strokewidth":0}},"width":198,"height":52,"resume":false,"useHandCursor":true,"id":"6ejDxaOLIoX_expandinglabel","events":[{"kind":"onclickoutside","actions":[{"kind":"if_action","condition":{"statement":{"kind":"compare","operator":"eq","valuea":"$Expanded","typea":"property","valueb":true,"typeb":"boolean"}},"thenActions":[{"kind":"object_action","command":"hidecomplete","objRef":{"type":"string","value":"_this"}}]}]}]},{"kind":"vectorshape","rotation":0,"accType":"button","cliptobounds":false,"defaultAction":"onrelease","shapemaskId":"","xPos":0,"yPos":0,"tabIndex":11,"tabEnabled":true,"xOffset":0,"yOffset":0,"rotateXPos":14,"rotateYPos":14,"scaleX":100,"scaleY":100,"alpha":100,"depth":2,"scrolling":true,"shuffleLock":false,"data":{"hotlinkId":"","accState":0,"vectorData":{"left":0,"top":0,"right":28,"bottom":28,"altText":"Marker","pngfb":false,"pr":{"l":"Lib","i":32}},"html5data":{"xPos":0,"yPos":0,"width":28,"height":28,"strokewidth":0}},"markerType":"none","width":28,"height":28,"resume":false,"useHandCursor":true,"id":"6ejDxaOLIoX"}],"actionstates":[{"kind":"state","name":"_default","actions":[{"kind":"setobjstate","stateRef":{"type":"string","value":"_default"},"objRef":{"type":"string","value":"6ejDxaOLIoX"}}],"clickdef":[{"kind":"objref","type":"string","value":"6ejDxaOLIoX"}]}],"shapemaskId":"","xPos":204,"yPos":418,"tabIndex":22,"tabEnabled":false,"xOffset":0,"yOffset":0,"rotateXPos":14,"rotateYPos":14,"scaleX":100,"scaleY":100,"alpha":100,"rotation":0,"depth":13,"scrolling":true,"shuffleLock":false,"width":28,"height":28,"resume":false,"useHandCursor":true,"id":"6ejDxaOLIoX","actionGroups":{"_show":{"kind":"actiongroup","actions":[{"kind":"show","transition":"appear","objRef":{"type":"string","value":"6ejDxaOLIoX_expandinglabel"}},{"kind":"show","transition":"appear","objRef":{"type":"string","value":"6ejDxaOLIoX"}}]}},"events":[{"kind":"onrollover","actions":[{"kind":"bringtofront","value":{"type":"string","value":"_this"}},{"kind":"object_action","command":"showtitle","objRef":{"type":"string","value":"6ejDxaOLIoX_expandinglabel"}}]},{"kind":"onrollout","actions":[{"kind":"object_action","command":"hidetitle","objRef":{"type":"string","value":"6ejDxaOLIoX_expandinglabel"}}]},{"kind":"ontransitionin","actions":[{"kind":"exe_actiongroup","id":"_show"}]}]},{"kind":"stategroup","objects":[{"kind":"expandinglabel","animationtype":"full","showclosebutton":false,"contentheight":0,"borderwidth":2,"arrowxpos":-18,"arrowypos":0,"textLib":[{"kind":"textdata","uniqueId":"6KT6FpqSsNF_-21946978","id":"01","linkId":"txt__default_6KT6FpqSsNF","type":"vectortext","xPos":0,"yPos":0,"width":0,"height":0,"shadowIndex":-1,"vectortext":{"left":0,"top":0,"right":117,"bottom":19,"pngfb":false,"pr":{"l":"Lib","i":790}}}],"shapemaskId":"","xPos":32,"yPos":14,"tabIndex":15,"tabEnabled":true,"xOffset":0,"yOffset":0,"rotateXPos":0,"rotateYPos":0,"scaleX":100,"scaleY":100,"alpha":100,"rotation":0,"depth":1,"scrolling":true,"shuffleLock":false,"colors":[{"kind":"color","name":"border","fill":{"type":"linear","rotation":0,"colors":[{"kind":"color","rgb":"0xFAC090","alpha":100,"stop":0}]}},{"kind":"color","name":"bg","fill":{"type":"linear","rotation":0,"colors":[{"kind":"color","rgb":"0xF2F2F2","alpha":100,"stop":0}]}}],"data":{"hotlinkId":"","accState":0,"vectorData":{"left":0,"top":0,"right":122,"bottom":19,"altText":"the splenic artery","pngfb":false,"pr":{"l":"Lib","i":789}},"html5data":{"xPos":0,"yPos":0,"width":122,"height":19,"strokewidth":0}},"width":132,"height":41,"resume":false,"useHandCursor":true,"id":"6KSf5bjKtRi_expandinglabel","events":[{"kind":"onclickoutside","actions":[{"kind":"if_action","condition":{"statement":{"kind":"compare","operator":"eq","valuea":"$Expanded","typea":"property","valueb":true,"typeb":"boolean"}},"thenActions":[{"kind":"object_action","command":"hidecomplete","objRef":{"type":"string","value":"_this"}}]}]}]},{"kind":"vectorshape","rotation":0,"accType":"button","cliptobounds":false,"defaultAction":"onrelease","shapemaskId":"","xPos":0,"yPos":0,"tabIndex":14,"tabEnabled":true,"xOffset":0,"yOffset":0,"rotateXPos":14,"rotateYPos":14,"scaleX":100,"scaleY":100,"alpha":100,"depth":2,"scrolling":true,"shuffleLock":false,"data":{"hotlinkId":"","accState":0,"vectorData":{"left":0,"top":0,"right":28,"bottom":28,"altText":"Marker","pngfb":false,"pr":{"l":"Lib","i":32}},"html5data":{"xPos":0,"yPos":0,"width":28,"height":28,"strokewidth":0}},"markerType":"none","width":28,"height":28,"resume":false,"useHandCursor":true,"id":"6KSf5bjKtRi"}],"actionstates":[{"kind":"state","name":"_default","actions":[{"kind":"setobjstate","stateRef":{"type":"string","value":"_default"},"objRef":{"type":"string","value":"6KSf5bjKtRi"}}],"clickdef":[{"kind":"objref","type":"string","value":"6KSf5bjKtRi"}]}],"shapemaskId":"","xPos":68,"yPos":466,"tabIndex":23,"tabEnabled":false,"xOffset":0,"yOffset":0,"rotateXPos":14,"rotateYPos":14,"scaleX":100,"scaleY":100,"alpha":100,"rotation":0,"depth":14,"scrolling":true,"shuffleLock":false,"width":28,"height":28,"resume":false,"useHandCursor":true,"id":"6KSf5bjKtRi","actionGroups":{"_show":{"kind":"actiongroup","actions":[{"kind":"show","transition":"appear","objRef":{"type":"string","value":"6KSf5bjKtRi_expandinglabel"}},{"kind":"show","transition":"appear","objRef":{"type":"string","value":"6KSf5bjKtRi"}}]}},"events":[{"kind":"onrollover","actions":[{"kind":"bringtofront","value":{"type":"string","value":"_this"}},{"kind":"object_action","command":"showtitle","objRef":{"type":"string","value":"6KSf5bjKtRi_expandinglabel"}}]},{"kind":"onrollout","actions":[{"kind":"object_action","command":"hidetitle","objRef":{"type":"string","value":"6KSf5bjKtRi_expandinglabel"}}]},{"kind":"ontransitionin","actions":[{"kind":"exe_actiongroup","id":"_show"}]}]}],"startTime":-1,"elapsedTimeMode":"normal","useHandCursor":false,"resume":false,"kind":"slidelayer","isBaseLayer":true}]}
