{"title":"Lab 6 Field Trip Specimens","trackViews":true,"showMenuResultIcon":false,"viewGroupId":"","historyGroupId":"","videoZoom":"","scrolling":false,"transition":"appear","transDuration":0,"transDir":1,"wipeTrans":false,"slideLock":false,"navIndex":-1,"globalAudioId":"","thumbnailid":"","presenterRef":{"id":"none"},"showAnimationId":"","lmsId":"Slide1","width":720,"height":540,"resume":false,"background":{"type":"fill","fill":{"type":"linear","rotation":90,"colors":[{"kind":"color","rgb":"0xFFFFFF","alpha":100,"stop":0}]}},"id":"5m4omosgadD","actionGroups":{"ActGrpOnSubmitButtonClick":{"kind":"actiongroup","actions":[]}},"events":[{"kind":"onbeforeslidein","actions":[{"kind":"if_action","condition":{"statement":{"kind":"compare","operator":"eq","valuea":"$WindowId","typea":"property","valueb":"_frame","typeb":"string"}},"thenActions":[{"kind":"set_frame_layout","name":"npnxnanbnsnfns01001000001"}],"elseActions":[{"kind":"set_window_control_layout","name":"npnxnanbnsnfns01001000001"}]}]},{"kind":"onsubmitslide","actions":[{"kind":"exe_actiongroup","id":"ActGrpOnSubmitButtonClick"}]},{"kind":"onkeypress","keycode":37,"shift":false,"ctrl":false,"alt":false,"actions":[{"kind":"history_prev"}]},{"kind":"ontransitionin","actions":[{"kind":"adjustvar","variable":"_player.LastSlideViewed_6lnQG5rZdmn","operator":"set","value":{"type":"string","value":"_player."}},{"kind":"adjustvar","variable":"_player.LastSlideViewed_6lnQG5rZdmn","operator":"add","value":{"type":"property","value":"$AbsoluteId"}}]}],"slideLayers":[{"enableSeek":true,"enableReplay":true,"timeline":{"duration":5000,"events":[{"kind":"ontimelinetick","time":0,"actions":[{"kind":"show","transition":"appear","objRef":{"type":"string","value":"5ytawQP9eFs"}},{"kind":"show","transition":"appear","objRef":{"type":"string","value":"6RtAuD9xJQP"}},{"kind":"show","transition":"appear","objRef":{"type":"string","value":"6liRGPAkiq7"}},{"kind":"show","transition":"appear","objRef":{"type":"string","value":"5jlJIfixV8E"}},{"kind":"show","transition":"appear","objRef":{"type":"string","value":"6DqseR6Vubn"}},{"kind":"show","transition":"appear","objRef":{"type":"string","value":"6WsPznnMKjp"}},{"kind":"show","transition":"appear","objRef":{"type":"string","value":"5lEIlxFaewA"}}]}]},"objects":[{"kind":"vectorshape","rotation":0,"accType":"image","cliptobounds":false,"defaultAction":"","imagelib":[{"kind":"imagedata","assetId":480,"id":"01","url":"story_content/67CZOpAeoOe_P_458_0_341_639_DX1136_DY1136.swf","type":"normal","altText":"Picture 1","width":341,"height":639,"mobiledx":0,"mobiledy":0}],"shapemaskId":"","xPos":473,"yPos":46,"tabIndex":2,"tabEnabled":true,"xOffset":0,"yOffset":0,"rotateXPos":121.5,"rotateYPos":227,"scaleX":100,"scaleY":100,"alpha":100,"depth":1,"scrolling":true,"shuffleLock":false,"data":{"hotlinkId":"","accState":0,"vectorData":{"left":0,"top":0,"right":243,"bottom":454,"altText":"Picture 1","pngfb":false,"pr":{"l":"Lib","i":1639}},"html5data":{"xPos":0,"yPos":0,"width":243,"height":454,"strokewidth":0}},"width":243,"height":454,"resume":false,"useHandCursor":true,"id":"5ytawQP9eFs"},{"kind":"vectorshape","rotation":0,"accType":"text","cliptobounds":false,"defaultAction":"","shapemaskId":"","xPos":-1,"yPos":-2,"tabIndex":0,"tabEnabled":true,"xOffset":0,"yOffset":0,"rotateXPos":360.5,"rotateYPos":24,"scaleX":100,"scaleY":100,"alpha":100,"depth":2,"scrolling":true,"shuffleLock":false,"data":{"hotlinkId":"","accState":0,"vectorData":{"left":0,"top":0,"right":721,"bottom":48,"altText":"Rectangle 1","pngfb":false,"pr":{"l":"Lib","i":43}},"html5data":{"xPos":-1,"yPos":-1,"width":722,"height":49,"strokewidth":0}},"width":721,"height":48,"resume":false,"useHandCursor":true,"id":"6RtAuD9xJQP"},{"kind":"vectorshape","rotation":0,"accType":"text","cliptobounds":false,"defaultAction":"","textLib":[{"kind":"textdata","uniqueId":"6liRGPAkiq7_-270451385","id":"01","linkId":"txt__default_6liRGPAkiq7","type":"vectortext","xPos":0,"yPos":0,"width":0,"height":0,"shadowIndex":-1,"vectortext":{"left":0,"top":0,"right":217,"bottom":29,"pngfb":false,"pr":{"l":"Lib","i":1640}}}],"shapemaskId":"","xPos":-2,"yPos":6,"tabIndex":1,"tabEnabled":true,"xOffset":0,"yOffset":0,"rotateXPos":161,"rotateYPos":17,"scaleX":100,"scaleY":100,"alpha":100,"depth":3,"scrolling":true,"shuffleLock":false,"data":{"hotlinkId":"","accState":0,"vectorData":{"left":0,"top":0,"right":322,"bottom":34,"altText":"Lab 6 Field Trip Specimens","pngfb":false,"pr":{"l":"Lib","i":45}},"html5data":{"xPos":-1,"yPos":-1,"width":323,"height":35,"strokewidth":0}},"width":322,"height":34,"resume":false,"useHandCursor":true,"id":"6liRGPAkiq7"},{"kind":"vectorshape","rotation":0,"accType":"text","cliptobounds":false,"defaultAction":"","shapemaskId":"","xPos":0,"yPos":502,"tabIndex":5,"tabEnabled":true,"xOffset":0,"yOffset":0,"rotateXPos":360.5,"rotateYPos":20,"scaleX":100,"scaleY":100,"alpha":100,"depth":4,"scrolling":true,"shuffleLock":false,"data":{"hotlinkId":"","accState":0,"vectorData":{"left":0,"top":0,"right":721,"bottom":40,"altText":"Rectangle 2","pngfb":false,"pr":{"l":"Lib","i":44}},"html5data":{"xPos":-1,"yPos":-1,"width":722,"height":41,"strokewidth":0}},"width":721,"height":40,"resume":false,"useHandCursor":true,"id":"5jlJIfixV8E"},{"kind":"vectorshape","rotation":0,"accType":"button","cliptobounds":false,"defaultAction":"onrelease","textLib":[{"kind":"textdata","uniqueId":"6DqseR6Vubn_-309966506","id":"01","linkId":"txt__default_6DqseR6Vubn","type":"vectortext","xPos":0,"yPos":0,"width":0,"height":0,"shadowIndex":-1,"vectortext":{"left":0,"top":0,"right":90,"bottom":22,"pngfb":false,"pr":{"l":"Lib","i":29}}}],"shapemaskId":"","xPos":8,"yPos":510,"tabIndex":6,"tabEnabled":true,"xOffset":0,"yOffset":0,"rotateXPos":52,"rotateYPos":12,"scaleX":100,"scaleY":100,"alpha":100,"depth":5,"scrolling":true,"shuffleLock":false,"data":{"hotlinkId":"","accState":0,"vectorData":{"left":-2,"top":-2,"right":105,"bottom":25,"altText":"Previous","pngfb":false,"pr":{"l":"Lib","i":28}},"html5data":{"xPos":-1,"yPos":-1,"width":105,"height":25,"strokewidth":2}},"width":104,"height":24,"resume":false,"useHandCursor":true,"id":"6DqseR6Vubn","events":[{"kind":"onrelease","actions":[{"kind":"history_prev"}]}]},{"kind":"vectorshape","rotation":0,"accType":"text","cliptobounds":false,"defaultAction":"","textLib":[{"kind":"textdata","uniqueId":"6WsPznnMKjp_1286611172","id":"01","linkId":"txt__default_6WsPznnMKjp","type":"vectortext","xPos":0,"yPos":0,"width":0,"height":0,"shadowIndex":-1,"vectortext":{"left":0,"top":0,"right":275,"bottom":231,"pngfb":false,"pr":{"l":"Lib","i":1642}}}],"shapemaskId":"","xPos":32,"yPos":176,"tabIndex":4,"tabEnabled":true,"xOffset":0,"yOffset":0,"rotateXPos":160,"rotateYPos":118,"scaleX":100,"scaleY":100,"alpha":100,"depth":6,"scrolling":true,"shuffleLock":false,"data":{"hotlinkId":"","accState":0,"vectorData":{"left":0,"top":0,"right":320,"bottom":236,"altText":"Head and Neck Section of the Museum\n\nPharynx:\nH47, H68\n\nLarynx\nH50, H51, H52, H53, H54\n\nNeck\nH71, H73, H74","pngfb":false,"pr":{"l":"Lib","i":1641}},"html5data":{"xPos":-1,"yPos":-1,"width":321,"height":237,"strokewidth":0}},"width":320,"height":236,"resume":false,"useHandCursor":true,"id":"6WsPznnMKjp"},{"kind":"vectorshape","rotation":0,"accType":"text","cliptobounds":false,"defaultAction":"","textLib":[{"kind":"textdata","uniqueId":"5lEIlxFaewA_2073915969","id":"01","linkId":"txt__default_5lEIlxFaewA","type":"vectortext","xPos":0,"yPos":0,"width":0,"height":0,"shadowIndex":-1,"vectortext":{"left":0,"top":0,"right":378,"bottom":62,"pngfb":false,"pr":{"l":"Lib","i":1644}}}],"shapemaskId":"","xPos":30,"yPos":68,"tabIndex":3,"tabEnabled":true,"xOffset":0,"yOffset":0,"rotateXPos":194,"rotateYPos":33.5,"scaleX":100,"scaleY":100,"alpha":100,"depth":7,"scrolling":true,"shuffleLock":false,"data":{"hotlinkId":"","accState":0,"vectorData":{"left":0,"top":0,"right":388,"bottom":67,"altText":"Take a trip to Grant’s M useum of Anatomy, MS1150, and examine the specimens below to gain a greater understanding of the material outlined in your lab tasks. ","pngfb":false,"pr":{"l":"Lib","i":1643}},"html5data":{"xPos":-1,"yPos":-1,"width":389,"height":68,"strokewidth":0}},"width":388,"height":67,"resume":false,"useHandCursor":true,"id":"5lEIlxFaewA"}],"startTime":-1,"elapsedTimeMode":"normal","useHandCursor":false,"resume":false,"kind":"slidelayer","isBaseLayer":true}]}
