{"title":"25. Summary","trackViews":true,"showMenuResultIcon":false,"viewGroupId":"","historyGroupId":"","videoZoom":"","scrolling":false,"transition":"appear","transDuration":0,"transDir":1,"wipeTrans":false,"slideLock":false,"navIndex":-1,"globalAudioId":"","thumbnailid":"","presenterRef":{"id":"none"},"showAnimationId":"","lmsId":"Slide25","width":720,"height":540,"resume":false,"background":{"type":"swf","imagedata":{"assetId":4,"url":"","type":"normal","width":0,"height":0,"mobiledx":0,"mobiledy":0}},"id":"6hyq0m2OZnA","actionGroups":{"ActGrpOnNextButtonClick":{"kind":"actiongroup","actions":[{"kind":"gotoplay","window":"_current","wndtype":"normal","objRef":{"type":"string","value":"_player.5z9r51a7Icv.5WyAHfyAwyz"}}]},"ActGrpOnPrevButtonClick":{"kind":"actiongroup","actions":[{"kind":"gotoplay","window":"_current","wndtype":"normal","objRef":{"type":"string","value":"_player.5z9r51a7Icv.6hyjz3pJXi4"}}]},"NavigationRestrictionNextSlide_6hyq0m2OZnA":{"kind":"actiongroup","actions":[{"kind":"exe_actiongroup","id":"ActGrpOnNextButtonClick"}]},"NavigationRestrictionPreviousSlide_6hyq0m2OZnA":{"kind":"actiongroup","actions":[{"kind":"exe_actiongroup","id":"ActGrpOnPrevButtonClick"}]}},"events":[{"kind":"onbeforeslidein","actions":[{"kind":"if_action","condition":{"statement":{"kind":"compare","operator":"eq","valuea":"$WindowId","typea":"property","valueb":"_frame","typeb":"string"}},"thenActions":[{"kind":"set_frame_layout","name":"npnxnanbnsnfns01001000011"}],"elseActions":[{"kind":"set_window_control_layout","name":"npnxnanbnsnfns01001000011"}]}]},{"kind":"onkeypress","keycode":39,"shift":false,"ctrl":false,"alt":false,"actions":[{"kind":"gotoplay","window":"_current","wndtype":"normal","objRef":{"type":"string","value":"_player.5z9r51a7Icv.5WyAHfyAwyz"}}]},{"kind":"onkeypress","keycode":37,"shift":false,"ctrl":false,"alt":false,"actions":[{"kind":"gotoplay","window":"_current","wndtype":"normal","objRef":{"type":"string","value":"_player.5z9r51a7Icv.6hyjz3pJXi4"}}]},{"kind":"onnextslide","actions":[{"kind":"exe_actiongroup","id":"NavigationRestrictionNextSlide_6hyq0m2OZnA"}]},{"kind":"onprevslide","actions":[{"kind":"exe_actiongroup","id":"NavigationRestrictionPreviousSlide_6hyq0m2OZnA"}]},{"kind":"ontransitionin","actions":[{"kind":"adjustvar","variable":"_player.LastSlideViewed_5ovaWTLp8lG","operator":"set","value":{"type":"string","value":"_player."}},{"kind":"adjustvar","variable":"_player.LastSlideViewed_5ovaWTLp8lG","operator":"add","value":{"type":"property","value":"$AbsoluteId"}}]}],"slideLayers":[{"enableSeek":true,"enableReplay":true,"timeline":{"duration":5000,"events":[{"kind":"ontimelinetick","time":0,"actions":[{"kind":"show","transition":"appear","objRef":{"type":"string","value":"6c8s6X4ri3F"}},{"kind":"show","transition":"appear","objRef":{"type":"string","value":"6erQwrAY8A9"}},{"kind":"show","transition":"appear","objRef":{"type":"string","value":"6qo6QzSbZKy"}},{"kind":"show","transition":"appear","objRef":{"type":"string","value":"6B9uKPwI5h0"}},{"kind":"show","transition":"appear","objRef":{"type":"string","value":"6G9kWyzbsml"}}]}]},"objects":[{"kind":"vectorshape","rotation":0,"accType":"button","cliptobounds":false,"defaultAction":"onrelease","textLib":[{"kind":"textdata","uniqueId":"6c8s6X4ri3F_719946572","id":"01","linkId":"txt__default_6c8s6X4ri3F","type":"vectortext","xPos":0,"yPos":0,"width":0,"height":0,"shadowIndex":-1,"vectortext":{"left":0,"top":0,"right":64,"bottom":22,"pngfb":false,"pr":{"l":"Lib","i":23}}}],"shapemaskId":"","xPos":624,"yPos":510,"tabIndex":4,"tabEnabled":true,"xOffset":0,"yOffset":0,"rotateXPos":44,"rotateYPos":12,"scaleX":100,"scaleY":100,"alpha":100,"depth":1,"scrolling":true,"shuffleLock":false,"data":{"hotlinkId":"","accState":0,"vectorData":{"left":-2,"top":-2,"right":89,"bottom":25,"altText":"Next","pngfb":false,"pr":{"l":"Lib","i":22}},"html5data":{"xPos":-1,"yPos":-1,"width":89,"height":25,"strokewidth":2}},"width":88,"height":24,"resume":false,"useHandCursor":true,"id":"6c8s6X4ri3F","events":[{"kind":"onrelease","actions":[{"kind":"gotoplay","window":"_current","wndtype":"normal","objRef":{"type":"string","value":"_player.5z9r51a7Icv.5WyAHfyAwyz"}}]}]},{"kind":"vectorshape","rotation":0,"accType":"button","cliptobounds":false,"defaultAction":"onrelease","textLib":[{"kind":"textdata","uniqueId":"6erQwrAY8A9_110302777","id":"01","linkId":"txt__default_6erQwrAY8A9","type":"vectortext","xPos":0,"yPos":0,"width":0,"height":0,"shadowIndex":-1,"vectortext":{"left":0,"top":0,"right":90,"bottom":22,"pngfb":false,"pr":{"l":"Lib","i":21}}}],"shapemaskId":"","xPos":8,"yPos":510,"tabIndex":3,"tabEnabled":true,"xOffset":0,"yOffset":0,"rotateXPos":52,"rotateYPos":12,"scaleX":100,"scaleY":100,"alpha":100,"depth":2,"scrolling":true,"shuffleLock":false,"data":{"hotlinkId":"","accState":0,"vectorData":{"left":-2,"top":-2,"right":105,"bottom":25,"altText":"Previous","pngfb":false,"pr":{"l":"Lib","i":20}},"html5data":{"xPos":-1,"yPos":-1,"width":105,"height":25,"strokewidth":2}},"width":104,"height":24,"resume":false,"useHandCursor":true,"id":"6erQwrAY8A9","events":[{"kind":"onrelease","actions":[{"kind":"gotoplay","window":"_current","wndtype":"normal","objRef":{"type":"string","value":"_player.5z9r51a7Icv.6hyjz3pJXi4"}}]}]},{"kind":"vectorshape","rotation":0,"accType":"text","cliptobounds":false,"defaultAction":"","textLib":[{"kind":"textdata","uniqueId":"6qo6QzSbZKy_-1063269761","id":"01","linkId":"txt__default_6qo6QzSbZKy","type":"vectortext","xPos":0,"yPos":0,"width":0,"height":0,"shadowIndex":-1,"vectortext":{"left":0,"top":0,"right":118,"bottom":26,"pngfb":false,"pr":{"l":"Lib","i":295}}}],"shapemaskId":"","xPos":6,"yPos":8,"tabIndex":1,"tabEnabled":true,"xOffset":0,"yOffset":0,"rotateXPos":197,"rotateYPos":14.5,"scaleX":100,"scaleY":100,"alpha":100,"depth":3,"scrolling":true,"shuffleLock":false,"data":{"hotlinkId":"","accState":0,"vectorData":{"left":0,"top":0,"right":394,"bottom":29,"altText":"H4   Summary","pngfb":false,"pr":{"l":"Lib","i":74}},"html5data":{"xPos":-1,"yPos":-1,"width":395,"height":30,"strokewidth":0}},"width":394,"height":29,"resume":false,"useHandCursor":true,"id":"6qo6QzSbZKy"},{"kind":"vectorshape","rotation":0,"accType":"text","cliptobounds":false,"defaultAction":"","textLib":[{"kind":"textdata","uniqueId":"6B9uKPwI5h0_1705440075","id":"01","linkId":"txt__default_6B9uKPwI5h0","type":"vectortext","xPos":0,"yPos":0,"width":0,"height":0,"shadowIndex":-1,"vectortext":{"left":0,"top":0,"right":677,"bottom":393,"pngfb":false,"pr":{"l":"Lib","i":296}}}],"shapemaskId":"","xPos":10,"yPos":48,"tabIndex":2,"tabEnabled":true,"xOffset":0,"yOffset":0,"rotateXPos":342,"rotateYPos":199,"scaleX":100,"scaleY":100,"alpha":100,"depth":4,"scrolling":true,"shuffleLock":false,"data":{"hotlinkId":"","accState":0,"vectorData":{"left":0,"top":0,"right":684,"bottom":398,"altText":"This module has described the: \nbasic structural differences between striated and smooth muscle\nbanding pattern of striated muscle\nstructure of thick and thin myofilaments\norganization of muscle fibres and connective tissues in a typical skeletal muscle\nroles of sarcoplasmic reticulum and T-tubules in skeletal muscle contraction\nbasic processes mediating contraction in striated muscle\nstructure and functional implications of a motor unit\nbasic structure of a neuromuscular junction\nstructural differences between skeletal, cardiac muscle and smooth muscle and how to identify each in light micrographs\ncontrol of muscular contraction in the different types of muscle tissue","pngfb":false,"pr":{"l":"Lib","i":76}},"html5data":{"xPos":-1,"yPos":-1,"width":685,"height":399,"strokewidth":0}},"width":684,"height":398,"resume":false,"useHandCursor":true,"id":"6B9uKPwI5h0"},{"kind":"vectorshape","rotation":0,"accType":"text","cliptobounds":false,"defaultAction":"","textLib":[{"kind":"textdata","uniqueId":"6G9kWyzbsml_57396472","id":"01","linkId":"txt__default_6G9kWyzbsml","type":"vectortext","xPos":0,"yPos":0,"width":0,"height":0,"shadowIndex":-1,"vectortext":{"left":0,"top":0,"right":92,"bottom":28,"pngfb":false,"pr":{"l":"Lib","i":297}}}],"shapemaskId":"","xPos":612,"yPos":6,"tabIndex":0,"tabEnabled":true,"xOffset":0,"yOffset":0,"rotateXPos":51,"rotateYPos":16.5,"scaleX":100,"scaleY":100,"alpha":100,"depth":5,"scrolling":true,"shuffleLock":false,"data":{"hotlinkId":"","accState":0,"vectorData":{"left":0,"top":0,"right":102,"bottom":33,"altText":"25","pngfb":false,"pr":{"l":"Lib","i":78}},"html5data":{"xPos":-1,"yPos":-1,"width":103,"height":34,"strokewidth":0}},"width":102,"height":33,"resume":false,"useHandCursor":true,"id":"6G9kWyzbsml"}],"startTime":-1,"elapsedTimeMode":"normal","useHandCursor":false,"resume":false,"kind":"slidelayer","isBaseLayer":true}]}
